cloud_products/__init__.py
cloud_products/aws.py
cloud_products/base.py
cloud_products/product.py
cloud_products-1.1.4.dist-info/LICENSE
cloud_products-1.1.4.dist-info/METADATA
cloud_products-1.1.4.dist-info/WHEEL
cloud_products-1.1.4.dist-info/top_level.txt
cloud_products-1.1.4.dist-info/RECORD
