Metadata-Version: 2.1
Name: cloud-products
Version: 1.1.4
Summary: A package for getting cloud product descriptions from the provider website.
Home-page: https://github.com/dylanhogg/cloud-products
Author: Dylan Hogg
Author-email: dylanhogg@gmail.com
License: UNKNOWN
Keywords: aws,crawler
Platform: UNKNOWN
Classifier: Development Status :: 5 - Production/Stable 
Classifier: Intended Audience :: Developers
Classifier: Topic :: Software Development
Classifier: Topic :: Text Processing
Classifier: License :: OSI Approved :: MIT License
Classifier: Programming Language :: Python :: 3
Requires-Python: >=3.6, <4
Requires-Dist: beautifulsoup4
